ytch/__init__.py
ytch/main.py
ytch/utils.py
ytch/static/baloo.woff
ytch-0.2.0.dist-info/METADATA
ytch-0.2.0.dist-info/WHEEL
ytch-0.2.0.dist-info/RECORD
