Metadata-Version: 2.4
Name: ytch
Version: 0.2.0
Summary: Chat, Transcript, and Summarize YouTube Videos with AI
Author-email: Kelvin Ng <hoishing@gmail.com>
Requires-Python: >=3.12
Requires-Dist: click>=8.2.1
Requires-Dist: google-genai>=1.25.0
Requires-Dist: python-dotenv>=1.1.1
Requires-Dist: pytubefix>=9.3.0
Requires-Dist: streamlit>=1.46.1
